transformer_lm_gan/__init__.py
transformer_lm_gan/transformer_lm_gan.py
transformer_lm_gan-0.0.3.dist-info/METADATA
transformer_lm_gan-0.0.3.dist-info/WHEEL
transformer_lm_gan-0.0.3.dist-info/licenses/LICENSE
transformer_lm_gan-0.0.3.dist-info/RECORD
