Metadata-Version: 2.4
Name: transformer-lm-gan
Version: 0.0.3
Summary: Explorations into Transformer Language Model with Adversarial Loss
Project-URL: Homepage, https://pypi.org/project/transformer-lm-gan/
Project-URL: Repository, https://github.com/lucidrains/transformer-lm-gan
Author-email: Phil Wang <lucidrains@gmail.com>
License: MIT License
License-File: LICENSE
Keywords: adversarial training,artificial intelligence,autoregressive transformer,deep learning
Classifier: Development Status :: 4 - Beta
Classifier: Intended Audience :: Developers
Classifier: License :: OSI Approved :: MIT License
Classifier: Programming Language :: Python :: 3.9
Classifier: Topic :: Scientific/Engineering :: Artificial Intelligence
Requires-Python: >=3.9
Requires-Dist: adam-atan2-pytorch>=0.1.18
Requires-Dist: einops>=0.8.0
Requires-Dist: einx>=0.3.0
Requires-Dist: torch>=2.0
Requires-Dist: vector-quantize-pytorch>=1.21.8
Requires-Dist: x-transformers>=2.0.0
Provides-Extra: examples
Requires-Dist: tqdm; extra == 'examples'
Provides-Extra: test
Requires-Dist: pytest; extra == 'test'
